awscli/help.py
awscli/text.py
awscli/argparser.py
awscli/shorthand.py
awscli/clidocs.py
awscli/table.py
awscli/testutils.py
awscli/plugin.py
awscli/completer.py
awscli/paramfile.py
awscli/schema.py
awscli/argprocess.py
awscli/arguments.py
awscli/errorhandler.py
awscli/__main__.py
awscli/utils.py
awscli/handlers.py
awscli/commands.py
awscli/topictags.py
awscli/clidriver.py
awscli/compat.py
awscli/formatter.py
awscli/__init__.py
awscli/alias.py
awscli/examples/waf-regional/update-ip-set.rst
awscli/examples/waf-regional/update-byte-match-set.rst
awscli/examples/waf-regional/update-sql-injection-match-set.rst
awscli/examples/waf-regional/update-web-acl.rst
awscli/examples/waf-regional/update-xss-match-set.rst
awscli/examples/waf-regional/associate-web-acl.rst
awscli/examples/waf-regional/update-rule.rst
awscli/examples/waf-regional/update-size-constraint-set.rst
awscli/examples/ec2/describe-instance-attribute.rst
awscli/examples/ec2/create-vpc-peering-connection.rst
awscli/examples/ec2/associate-route-table.rst
awscli/examples/ec2/describe-vpc-endpoint-service-configurations.rst
awscli/examples/ec2/get-launch-template-data.rst
awscli/examples/ec2/release-hosts.rst
awscli/examples/ec2/create-security-group.rst
awscli/examples/ec2/create-network-interface.rst
awscli/examples/ec2/create-vpc-endpoint-connection-notification.rst
awscli/examples/ec2/accept-vpc-peering-connection.rst
awscli/examples/ec2/unassign-private-ip-addresses.rst
awscli/examples/ec2/attach-network-interface.rst
awscli/examples/ec2/describe-snapshot-attribute.rst
awscli/examples/ec2/describe-subnets.rst
awscli/examples/ec2/modify-identity-id-format.rst
awscli/examples/ec2/describe-internet-gateways.rst
awscli/examples/ec2/terminate-instances.rst
awscli/examples/ec2/reboot-instances.rst
awscli/examples/ec2/restore-address-to-classic.rst
awscli/examples/ec2/cancel-bundle-task.rst
awscli/examples/ec2/create-vpn-connection-route.rst
awscli-1.16.137.dist-info/WHEEL
awscli-1.16.137.dist-info/DESCRIPTION.rst
awscli-1.16.137.dist-info/metadata.json
awscli-1.16.137.dist-info/METADATA
awscli-1.16.137.dist-info/RECORD
awscli-1.16.137.dist-info/top_level.txt
