Metadata-Version: 2.0
Name: awscli
Version: 1.16.137
Summary: Universal Command Line Environment for AWS.
Home-page: http://aws.amazon.com/cli/
Author: Amazon Web Services
Author-email: UNKNOWN
License: Apache License 2.0
Platform: UNKNOWN
Classifier: Development Status :: 5 - Production/Stable
Classifier: Intended Audience :: Developers
Classifier: Intended Audience :: System Administrators
Classifier: Natural Language :: English
Classifier: License :: OSI Approved :: Apache Software License
Classifier: Programming Language :: Python
Classifier: Programming Language :: Python :: 2
Classifier: Programming Language :: Python :: 2.6
Classifier: Programming Language :: Python :: 2.7
Classifier: Programming Language :: Python :: 3
Classifier: Programming Language :: Python :: 3.3
Classifier: Programming Language :: Python :: 3.4
Classifier: Programming Language :: Python :: 3.5
Classifier: Programming Language :: Python :: 3.6
Classifier: Programming Language :: Python :: 3.7
Requires-Dist: botocore==1.12.127
Requires-Dist: colorama>=0.2.5,<=0.3.9
Requires-Dist: docutils>=0.10
Requires-Dist: rsa>=3.1.2,<=3.5.0
Requires-Dist: PyYAML>=3.10,<=3.13
Requires-Dist: s3transfer>=0.2.0,<0.3.0
Requires-Dist: argparse>=1.1; python_version=="2.6"
